README.md
beancount_allocate/__init__.py
beancount_allocate/allocate.py
beancount_allocate/common.py
beancount_allocate-0.1.4.dist-info/LICENSE
beancount_allocate-0.1.4.dist-info/METADATA
beancount_allocate-0.1.4.dist-info/WHEEL
beancount_allocate-0.1.4.dist-info/top_level.txt
beancount_allocate-0.1.4.dist-info/RECORD
