Metadata-Version: 2.1
Name: beancount-allocate
Version: 0.1.4
Summary: Plugin for Beancount to collaborate within one ledger.
Home-page: https://github.com/Akuukis/beancount_allocate
Author: Akuukis
Author-email: akuukis@kalvis.lv
License: GNU AGPLv3
Download-URL: https://pypi.python.org/pypi/beancount_allocate
Platform: UNKNOWN
Requires-Dist: beancount (>=2.0)
Requires-Dist: beancount-plugin-utils (>=0.0.4)
